complicated/__init__.py
complicated/lib.py
complicated-1.0.0.data/scripts/complicated
complicated-1.0.0.dist-info/METADATA
complicated-1.0.0.dist-info/WHEEL
complicated-1.0.0.dist-info/top_level.txt
complicated-1.0.0.dist-info/RECORD
