Metadata-Version: 2.1
Name: complicated
Version: 1.0.0
Summary: Complicated python api. Control Apple Watch Complications with WebHooks
Home-page: https://github.com/frenchie4111/complicated-python
Author: Mike Lyons
Author-email: mdl0394@gmail.com
License: MIT
Platform: UNKNOWN
Requires-Dist: requests
